README.rst
setup.cfg
setup.py
findcmd/__init__.py
findcmd/colors.py
findcmd/findcmd.py
findcmd.egg-info/PKG-INFO
findcmd.egg-info/SOURCES.txt
findcmd.egg-info/dependency_links.txt
findcmd.egg-info/entry_points.txt
findcmd.egg-info/not-zip-safe
findcmd.egg-info/top_level.txt