Metadata-Version: 1.1
Name: findcmd
Version: 0.1.2
Summary: A command line tool for searching commands
Home-page: https://github.com/xupeng/findcmd
Author: Xupeng Yun
Author-email: xupeng@xupeng.me
License: Apache-2.0
Keywords: console sysutils
Platform: UNKNOWN
Classifier: Environment :: Console
Classifier: Operating System :: MacOS
Classifier: Operating System :: POSIX :: Linux
Classifier: Operating System :: POSIX :: BSD
Classifier: Operating System :: Unix
Classifier: Programming Language :: Python
Classifier: Topic :: System :: Systems Administration
Classifier: Topic :: Utilities
